README
setup.py
urlunshort/__init__.py
urlunshort/console.py
urlunshort/resolvers.py
urlunshort.egg-info/PKG-INFO
urlunshort.egg-info/SOURCES.txt
urlunshort.egg-info/dependency_links.txt
urlunshort.egg-info/entry_points.txt
urlunshort.egg-info/not-zip-safe
urlunshort.egg-info/top_level.txt