Metadata-Version: 1.0
Name: urlunshort
Version: 0.2.4
Summary: Tools for detecting and expanding shortened URLs.
Home-page: http://bitbucket.org/runeh/urlunshort
Author: Rune Halvorsen
Author-email: runefh@gmail.com
License: BSD
Platform: UNKNOWN
Classifier: Intended Audience :: Developers
Classifier: License :: OSI Approved :: BSD License
Classifier: Operating System :: OS Independent
Classifier: Topic :: Internet :: WWW/HTTP
